aliyunsdkswas_open/__init__.py
aliyunsdkswas_open/request/__init__.py
aliyunsdkswas_open/request/v20200601/AddCustomImageShareAccountRequest.py
aliyunsdkswas_open/request/v20200601/AllocatePublicConnectionRequest.py
aliyunsdkswas_open/request/v20200601/ApplyFirewallTemplateRequest.py
aliyunsdkswas_open/request/v20200601/AttachKeyPairRequest.py
aliyunsdkswas_open/request/v20200601/CreateCommandRequest.py
aliyunsdkswas_open/request/v20200601/CreateCustomImageRequest.py
aliyunsdkswas_open/request/v20200601/CreateFirewallRuleRequest.py
aliyunsdkswas_open/request/v20200601/CreateFirewallRulesRequest.py
aliyunsdkswas_open/request/v20200601/CreateFirewallTemplateRequest.py
aliyunsdkswas_open/request/v20200601/CreateFirewallTemplateRulesRequest.py
aliyunsdkswas_open/request/v20200601/CreateInstanceKeyPairRequest.py
aliyunsdkswas_open/request/v20200601/CreateInstancesRequest.py
aliyunsdkswas_open/request/v20200601/CreateKeyPairRequest.py
aliyunsdkswas_open/request/v20200601/CreateSnapshotRequest.py
aliyunsdkswas_open/request/v20200601/DeleteCommandRequest.py
aliyunsdkswas_open/request/v20200601/DeleteCustomImageRequest.py
aliyunsdkswas_open/request/v20200601/DeleteCustomImagesRequest.py
aliyunsdkswas_open/request/v20200601/DeleteFirewallRuleRequest.py
aliyunsdkswas_open/request/v20200601/DeleteFirewallRulesRequest.py
aliyunsdkswas_open/request/v20200601/DeleteFirewallTemplateRulesRequest.py
aliyunsdkswas_open/request/v20200601/DeleteFirewallTemplatesRequest.py
aliyunsdkswas_open/request/v20200601/DeleteInstanceKeyPairRequest.py
aliyunsdkswas_open/request/v20200601/DeleteKeyPairsRequest.py
aliyunsdkswas_open/request/v20200601/DeleteSnapshotRequest.py
aliyunsdkswas_open/request/v20200601/DeleteSnapshotsRequest.py
aliyunsdkswas_open/request/v20200601/DescribeCloudAssistantAttributesRequest.py
aliyunsdkswas_open/request/v20200601/DescribeCloudAssistantStatusRequest.py
aliyunsdkswas_open/request/v20200601/DescribeCloudMonitorAgentStatusesRequest.py
aliyun_python_sdk_swas_open-1.0.14.dist-info/LICENSE
aliyun_python_sdk_swas_open-1.0.14.dist-info/METADATA
aliyun_python_sdk_swas_open-1.0.14.dist-info/WHEEL
aliyun_python_sdk_swas_open-1.0.14.dist-info/top_level.txt
aliyun_python_sdk_swas_open-1.0.14.dist-info/RECORD
